britney/__init__.py
britney/core.py
britney/errors.py
britney/request.py
britney/utils.py
britney/middleware/__init__.py
britney/middleware/auth.py
britney/middleware/base.py
britney/middleware/format.py
britney/middleware/utils.py
britney-0.5.1.dist-info/DESCRIPTION.rst
britney-0.5.1.dist-info/METADATA
britney-0.5.1.dist-info/RECORD
britney-0.5.1.dist-info/WHEEL
britney-0.5.1.dist-info/metadata.json
britney-0.5.1.dist-info/top_level.txt
