Metadata-Version: 2.0
Name: britney
Version: 0.5.1
Summary: Python implementation of SPORE
Home-page: https://github.com/agrausem/britney
Author: Arnaud Grausem
Author-email: arnaud.grausem@gmail.com
License: PSF
Download-URL: http://pypi.python.org/pypi/britney
Keywords: SPORE,REST Api,client
Platform: UNKNOWN
Classifier: Development Status :: 4 - Beta
Classifier: Environment :: Web Environment
Classifier: Intended Audience :: Developers
Classifier: License :: OSI Approved :: BSD License
Classifier: Operating System :: OS Independent
Classifier: Programming Language :: Python :: 2.7
Classifier: Programming Language :: Python :: 3.2
Classifier: Programming Language :: Python :: 3.3
Classifier: Programming Language :: Python :: 3.4
Classifier: Programming Language :: Python :: 3.5
Classifier: Programming Language :: Python :: 3.6
Requires-Dist: requests
Requires-Dist: requests-testadapter
